draftail_maths/__init__.py
draftail_maths/apps.py
draftail_maths/default_settings.py
draftail_maths/maths_feature_names.py
draftail_maths/maths_features.py
draftail_maths/wagtail_hooks.py
draftail_maths/static/draftail_maths/css/draftail_maths.css
draftail_maths/static/draftail_maths/css/draftail_maths_frontend.css
draftail_maths/static/draftail_maths/js/draftail_maths.js
draftail_maths/templates/draftail_maths/tags/support.html
draftail_maths/templatetags/__init__.py
draftail_maths/templatetags/draftail_maths_tags.py
draftail_maths-4.1.0.dist-info/AUTHORS.txt
draftail_maths-4.1.0.dist-info/LICENSE.txt
draftail_maths-4.1.0.dist-info/METADATA
draftail_maths-4.1.0.dist-info/WHEEL
draftail_maths-4.1.0.dist-info/top_level.txt
draftail_maths-4.1.0.dist-info/zip-safe
draftail_maths-4.1.0.dist-info/RECORD
