Metadata-Version: 2.1
Name: draftail-maths
Version: 4.1.0
Summary: A maths extension for the Draftail editor of Wagtail.
Home-page: https://github.com/high-dimensional/draftail-maths
Author: High Dimensional Neurology Group, UCL
Author-email: pypi@highdimensional.net
License: BSD-3-Clause
Platform: any
Classifier: Framework :: Django
Classifier: Framework :: Wagtail
Classifier: Programming Language :: Python :: 3
Classifier: Programming Language :: Python :: 3.8
Classifier: License :: OSI Approved :: BSD License
Classifier: Operating System :: OS Independent
Requires-Python: >=3.8
License-File: LICENSE.txt
License-File: AUTHORS.txt
Requires-Dist: Django (<4.2,>=4.1)
Requires-Dist: wagtail (<4.2,>=4.1)
Requires-Dist: django-auxiliaries (<4.2,>=4.1)
Requires-Dist: draftail-helpers (<4.2,>=4.1)
Requires-Dist: tour-guide (<4.2,>=4.1)
